alliance_platform/py.typed
alliance_platform/storage/__init__.py
alliance_platform/storage/apps.py
alliance_platform/storage/async_uploads/forms.py
alliance_platform/storage/async_uploads/models.py
alliance_platform/storage/async_uploads/registry.py
alliance_platform/storage/async_uploads/rest_framework/__init__.py
alliance_platform/storage/async_uploads/rest_framework/serializer.py
alliance_platform/storage/async_uploads/storage/azure.py
alliance_platform/storage/async_uploads/storage/base.py
alliance_platform/storage/async_uploads/storage/filesystem.py
alliance_platform/storage/async_uploads/storage/s3.py
alliance_platform/storage/async_uploads/views/__init__.py
alliance_platform/storage/async_uploads/views/api.py
alliance_platform/storage/async_uploads/views/filesystem.py
alliance_platform/storage/management/commands/cleanup_async_temp_files.py
alliance_platform/storage/migrations/0001_initial.py
alliance_platform/storage/migrations/0002_migrate_common_storage.py
alliance_platform/storage/migrations/__init__.py
alliance_platform/storage/models.py
alliance_platform/storage/settings.py
alliance_platform/storage/staticfiles/__init__.py
alliance_platform/storage/staticfiles/storage.py
alliance_platform_storage-0.0.4.dist-info/METADATA
alliance_platform_storage-0.0.4.dist-info/WHEEL
alliance_platform_storage-0.0.4.dist-info/entry_points.txt
alliance_platform_storage-0.0.4.dist-info/RECORD
